{
    "mode_name": "search",
    "init_activated": true,
    "templates": {
        "Home": {
            "common_info": {
                "priority": 5,
                "contrary": false,
                "precondition": [],
                "outcome": [],
                "consume": []
            },
            "detector": {
                "type": "FIXED_REGION",
                "kwargs": {
                    "template_name": "Home",
                    "threshold": 0.94,
                    "match_method": "TM_SQDIFF_NORMED",
                    "region": [
                        47,
                        918,
                        26,
                        34
                    ],
                    "template_image": "data/templates_matching/600x960\\TapTap\\templates\\search\\Home.jpg"
                }
            },
            "operations": [
                {
                    "type": "TAP",
                    "kwargs": {
                        "x": 62,
                        "y": 45
                    }
                },
                {
                    "type": "TAP",
                    "kwargs": {
                        "x": 63,
                        "y": 46
                    }
                }
            ]
        }
    }
}